swarmauri_certs_azure/__init__.py
swarmauri_certs_azure/certs/AzureKeyVaultCertService.py
swarmauri_certs_azure/certs/__init__.py
swarmauri_certs_azure-0.3.0.dev4.dist-info/METADATA
swarmauri_certs_azure-0.3.0.dev4.dist-info/WHEEL
swarmauri_certs_azure-0.3.0.dev4.dist-info/RECORD
